{
  "id": "40944003XX",
  "reaction": {
    "x4code": "(79-AU-197(N,G)79-AU-198,,SIG)",
    "target": "79-AU-197",
    "process": "N,G",
    "sf4": "79-AU-198",
    "residual": null,
    "sf5": null,
    "sf6": "SIG",
    "sf7": null,
    "sf8": null,
    "sf9": null,
    "freetext": []
  },
  "measurement_conditions": {
    "DECAY-DATA": {
      "XX": {
        "0": {
          "x4code": [
            "(79-AU-198,,DG,412.)"
          ],
          "freetext": [
            ""
          ]
        }
      }
    },
    "SAMPLE": {
      "XX": {
        "0": {
          "freetext": [
            " GOLD FOILS OF DIFFENTE THICKNESS WRAPPED IN",
            " INDIUM FOILS"
          ]
        }
      }
    }
  },
  "common_data": {
    "heads": [
      "EN",
      "MONIT",
      "MONIT-ERR"
    ],
    "units": [
      "MEV",
      "MB",
      "MB"
    ],
    "data": [
      [
        2.7
      ],
      [
        340.0
      ],
      [
        20.0
      ]
    ]
  },
  "data_table": {
    "heads": [
      "DATA",
      "DATA-ERR"
    ],
    "units": [
      "MB",
      "MB"
    ],
    "data": [
      [
        33.0
      ],
      [
        4.0
      ]
    ]
  }
}