{
  "id": "208680174",
  "reaction": {
    "x4code": "(94-PU-239(N,F),,SIG,,SPA)",
    "target": "94-PU-239",
    "process": "N,F",
    "sf4": null,
    "residual": null,
    "sf5": null,
    "sf6": "SIG",
    "sf7": null,
    "sf8": "SPA",
    "sf9": null,
    "freetext": []
  },
  "measurement_conditions": {
    "SAMPLE": {
      "XX": {
        "0": {
          "freetext": [
            ".About 0.1 mg/cm2 Pu electroplated onto a 1 mm thick",
            " nickel backing. Isotopic composition, 98.358% Pu-239,",
            " 1.613% Pu-240, 0.029% Pu-241 and less",
            "                                than 0.0005% Pu-242."
          ]
        }
      }
    }
  },
  "common_data": {
    "heads": [
      "EN-DUMMY"
    ],
    "units": [
      "MEV"
    ],
    "data": [
      [
        4.5
      ]
    ]
  },
  "data_table": {
    "heads": [
      "DATA      4",
      "DATA-ERR  4"
    ],
    "units": [
      "MB",
      "MB"
    ],
    "data": [
      [
        1820.0
      ],
      [
        60.0
      ]
    ]
  }
}