{
  "id": "11447072XX",
  "reaction": {
    "x4code": "(47-AG-107(N,G)47-AG-108,,SIG,,SPA/A)",
    "target": "47-AG-107",
    "process": "N,G",
    "sf4": "47-AG-108",
    "residual": null,
    "sf5": null,
    "sf6": "SIG",
    "sf7": null,
    "sf8": "SPA/A",
    "sf9": null,
    "freetext": []
  },
  "measurement_conditions": {
    "DECAY-DATA": {
      "XX": {
        "0": {
          "x4code": [
            "(47-AG-108-G,2.MIN,B)"
          ],
          "freetext": [
            ""
          ]
        }
      }
    },
    "INC-SPECT": {
      "XX": {
        "0": {
          "freetext": [
            "Reactor spectrum"
          ]
        }
      }
    }
  },
  "common_data": {
    "heads": [
      "EN-DUMMY"
    ],
    "units": [
      "EV"
    ],
    "data": [
      [
        0.0253
      ]
    ]
  },
  "data_table": {
    "heads": [
      "DATA",
      "DATA-ERR"
    ],
    "units": [
      "B",
      "PER-CENT"
    ],
    "data": [
      [
        0.05
      ],
      [
        20.0
      ]
    ]
  }
}