{
  "id": "40839009XX",
  "reaction": {
    "x4code": "(92-U-238(N,EL)92-U-238,,SIG,,SPA)",
    "target": "92-U-238",
    "process": "N,EL",
    "sf4": "92-U-238",
    "residual": null,
    "sf5": null,
    "sf6": "SIG",
    "sf7": null,
    "sf8": "SPA",
    "sf9": null,
    "freetext": []
  },
  "measurement_conditions": {},
  "common_data": {
    "heads": [
      "MONIT",
      "MONIT-ERR"
    ],
    "units": [
      "B",
      "B"
    ],
    "data": [
      [
        11.41
      ],
      [
        0.07
      ]
    ]
  },
  "data_table": {
    "heads": [
      "EN-MEAN",
      "DATA",
      "ERR-S"
    ],
    "units": [
      "KEV",
      "B",
      "B"
    ],
    "data": [
      [
        24.5
      ],
      [
        13.91
      ],
      [
        0.05
      ]
    ]
  }
}