{
  "id": "41455014XX",
  "reaction": {
    "x4code": "(82-PB-0(N,F),,SIG)",
    "target": "82-PB-0",
    "process": "N,F",
    "sf4": null,
    "residual": null,
    "sf5": null,
    "sf6": "SIG",
    "sf7": null,
    "sf8": null,
    "sf9": null,
    "freetext": []
  },
  "measurement_conditions": {
    "ERR-ANALYS": {
      "XX": {
        "0": {
          "x4code": "(ERR-S)",
          "freetext": [
            " Statistics"
          ]
        }
      }
    },
    "MONIT-REF": {
      "XX": {
        "0": {
          "x4code": {
            "type": null,
            "ent": null,
            "author": "A.Carlson+",
            "ref": "R,INDC(NDS)-368,23,1997"
          },
          "freetext": [
            ""
          ]
        }
      }
    },
    "MONITOR": {
      "XX": {
        "0": {
          "x4code": [
            "(92-U-235(N,F),,SIG)"
          ],
          "freetext": [
            ""
          ]
        }
      }
    }
  },
  "common_data": null,
  "data_table": {
    "heads": [
      "EN",
      "DATA",
      "ERR-S"
    ],
    "units": [
      "MEV",
      "MB",
      "MB"
    ],
    "data": [
      [
        30.36,
        31.37,
        32.43,
        33.56,
        34.74,
        35.98,
        37.3,
        38.69,
        40.16,
        41.72,
        43.37,
        45.13,
        47.0,
        48.99,
        51.11,
        53.37,
        55.8,
        58.4,
        61.19,
        64.2,
        67.44,
        70.94,
        74.73,
        78.84,
        83.32,
        88.22,
        93.57,
        99.46,
        105.96,
        113.14,
        121.14,
        130.07,
        140.1,
        151.44,
        164.33,
        179.09,
        196.15
      ],
      [
        0.08035,
        0.02993,
        0.08944,
        0.03709,
        0.06453,
        0.01254,
        0.0107,
        0.09228,
        0.1182,
        0.2962,
        0.2357,
        0.3236,
        0.4277,
        0.7985,
        1.025,
        1.331,
        1.608,
        1.841,
        2.257,
        2.95,
        3.438,
        4.207,
        5.09,
        5.903,
        6.909,
        8.016,
        9.59,
        10.87,
        12.18,
        14.19,
        16.47,
        18.8,
        21.73,
        25.49,
        28.66,
        33.0,
        38.22
      ],
      [
        0.02649,
        0.01338,
        0.02331,
        0.01616,
        0.01984,
        0.00795,
        0.00721,
        0.02072,
        0.02268,
        0.03542,
        0.03111,
        0.03569,
        0.04038,
        0.05443,
        0.06038,
        0.0677,
        0.07326,
        0.07683,
        0.08344,
        0.09361,
        0.09906,
        0.1076,
        0.116,
        0.1221,
        0.1289,
        0.1361,
        0.1456,
        0.1521,
        0.1578,
        0.1674,
        0.1782,
        0.1884,
        0.2013,
        0.2185,
        0.2318,
        0.2504,
        0.2752
      ]
    ]
  }
}